counter.v
//
//  counter.v
//  Counter Module
//
//  Created  by Juan Diego Ocampo on 03/05/2018.
//  Copyright © 2018 Juan Diego Ocampo. All rights reserved.
//

module counter(clk,period,duty,state,en); // Period nad DutyCycle are given in ms.
// Inputs and Outputs
	input clk;
	input en;
	input [31:0] period;
	input [31:0] duty;
	output reg state;
// Registers
reg [5:0] contusec = 0;
reg [14:0] contmsec = 0;
reg [4:0] periodf = 0;
reg [4:0] dutyf = 0;

	always @(posedge clk) begin
		if(en == 1)begin
			if(contusec == 50) begin // Counter registers 50 CLK Cycles, which equals to 1us (for a 50 MHz CLK).
				contusec = 0;
				if(contmsec >= period-1) begin // Period is registered in ms.
					contmsec = 0;
				end else begin
					contmsec = contmsec + 1;
				end
			end else begin
				contusec = contusec + 1;
			end
		end
	end

	always @(posedge clk) begin
		if(en == 1)begin
			if(contmsec <= duty-1)begin
				state = 1;
			end else begin
				state = 0;
			end
		end
	end

/*
	always @(posedge clk) begin

		if(en == 1)begin
			dutyf = duty;
			periodf = period;
		end
	end
*/

endmodule

pwm.v
//
//  pwm.v
//  Top level Verilog code for PWM Generator
//
//  Created  by Juan Diego Ocampo on 03/05/2018.
//  Copyright © 2018 Juan Diego Ocampo. All rights reserved.
//

`timescale 1ms / 1ns

module pwm(clk,rst,rd,wr,din,adrs,dout,pwmo);
// Inputs and Outputs
	input clk;
	input rst;
	input rd;
	input wr;
	input [31:00] din;
	input [6:0] adrs;
	output reg [31:00] dout;
	output [7:0] pwmo;
// Registers
reg [31:00] dinf;
reg [31:00] period0;
reg [31:00] period1;
reg [31:00] period2;
reg [31:00] period3;
reg [31:00] period4;
reg [31:00] period5;
reg [31:00] period6;
reg [31:00] period7;
reg [31:00] duty0;
reg [31:00] duty1;
reg [31:00] duty2;
reg [31:00] duty3;
reg [31:00] duty4;
reg [31:00] duty5;
reg [31:00] duty6;
reg [31:00] duty7;
reg en0;
reg en1;
reg en2;
reg en3;
reg en4;
reg en5;
reg en6;
reg en7;

/* Counter */

counter pwm0(.clk(clk), .period(period0), .duty(duty0), .state(pwmo[0]), .en(en0));
counter pwm1(.clk(clk), .period(period1), .duty(duty1), .state(pwmo[1]), .en(en1));
counter pwm2(.clk(clk), .period(period2), .duty(duty2), .state(pwmo[2]), .en(en2));
counter pwm3(.clk(clk), .period(period3), .duty(duty3), .state(pwmo[3]), .en(en3));
counter pwm4(.clk(clk), .period(period4), .duty(duty4), .state(pwmo[4]), .en(en4));
counter pwm5(.clk(clk), .period(period5), .duty(duty5), .state(pwmo[5]), .en(en5));
counter pwm6(.clk(clk), .period(period6), .duty(duty6), .state(pwmo[6]), .en(en6));
counter pwm7(.clk(clk), .period(period7), .duty(duty7), .state(pwmo[7]), .en(en7));

	always @(posedge clk) begin
		if(wr == 1) begin
			dinf = din;
			case(adrs)
				7'h00: en0 = dinf;
				7'h04: period0 = dinf;
				7'h08: duty0 = dinf;

				7'h0c: en1 = dinf;
				7'h10: period1 = dinf;
				7'h14: duty1 = dinf;
				
				7'h18: en2 = dinf;
				7'h1c: period2 = dinf;
				7'h20: duty2 = dinf;
				
				7'h24: en3 = dinf;
				7'h28: period3 = dinf;
				7'h2c: duty3 = dinf;
				
				7'h30: en4 = dinf;
				7'h34: period4 = dinf;
				7'h38: duty4 = dinf;
				
				7'h3c: en5 = dinf;
				7'h40: period5 = dinf;
				7'h44: duty5 = dinf;
				
				7'h48: en6 = dinf;
				7'h4c: period6 = dinf;
				7'h50: duty6 = dinf;
				
				7'h54: en7 = dinf;
				7'h58: period7 = dinf;
				7'h5c: duty7 = dinf;			
			default
				dinf = din;	
			endcase
		end
		
		if(rd == 1) begin
			case(adrs)
				6'h00: dout = en0;
				6'h04: dout = period0;
				6'h08: dout = duty0;
				
				6'h0c: dout = en1;
				6'h10: dout = period1;
				6'h14: dout = duty1;
				
				6'h18: dout = en2;
				6'h1c: dout = period2;
				6'h20: dout = duty2;
				
				6'h24: dout = en3;
				6'h28: dout = period3;
				6'h2c: dout = duty3;
				
				6'h30: dout = en4;
				6'h34: dout = period4;
				6'h38: dout = duty4;
				
				6'h3c: dout = en5;
				6'h40: dout = period5;
				6'h44: dout = duty5;
				
				6'h48: dout = en6;
				6'h4c: dout = period6;
				6'h50: dout = duty6;
				
				6'h54: dout = en7;
				6'h58: dout = period7;
				6'h5c: dout = duty7;
			default
				dinf = din;	
			endcase
		end
	end

endmodule

pwm_TB.v
//
//  pwm_TB.v
//  TestBench File for PWM Generator
//
//  Created  by Juan Diego Ocampo on 03/05/2018.
//  Copyright © 2018 Juan Diego Ocampo. All rights reserved.
//

`timescale 1ns / 1ns

module pwm_TB;
// Registers and Wires
	reg clk;
	reg rst;
	reg rd;
	reg wr;
	reg [31:0] din;
	reg [6:0] adrs;
	wire [31:0] dout;
	wire [7:0] pwmo;
	
	pwm uut( .clk(clk), .rst(rst), .rd(rd), .wr(wr), .din(din), .adrs(adrs), .dout(dout), .pwmo(pwmo));
	
// CLK Generator Module

	initial   clk <= 1;
	always #1 clk <= ~clk;

	initial begin
		
		wr = 1;
		din = 2;
		adrs = 7'h08;
		#2;
		din = 20;
		adrs = 7'h04;
		#2;
		din = 1;
		adrs = 7'h00;
		#2;
		
		din = 4;
		adrs = 7'h14;
		#2;
		din = 20;
		adrs = 7'h10;
		#2;
		din = 1;
		adrs = 7'h0c;
		#2;
		
		din = 2;
		adrs = 7'h20;
		#2;
		din = 20;
		adrs = 7'h1c;
		#2;
		din = 1;
		adrs = 7'h18;
		#2;
		
		din = 2;
		adrs = 7'h44;
		#2;
		din = 20;
		adrs = 7'h40;
		#2;
		din = 1;
		adrs = 7'h3c;
		#2;
		
		din = 2;
		adrs = 7'h5c;
		#2;
		din = 20;
		adrs = 7'h58;
		#2;
		din = 1;
		adrs = 7'h54;
		#2;
		
		wr = 0;
		rd = 1;
		adrs = 7'h04;
		#2;
		adrs = 7'h18;
		#2;
		adrs = 7'h5c;
		#2;
		adrs = 7'h00;
		#2;
		adrs = 7'h0;
	end

	initial begin: TEST_CASE
		$dumpfile("pwm_TB.vcd");
		$dumpvars(-1,uut);
		#(100000) $finish;
	end

endmodule

simulation/pwm_TB.vcd
$date
	Tue Feb 27 19:33:36 2018
$end
$version
	Icarus Verilog
$end
$timescale
	1ns
$end
$scope module pwm_TB $end
$scope module uut $end
$var wire 7 ! adrs [6:0] $end
$var wire 1 " clk $end
$var wire 32 # din [31:0] $end
$var wire 8 $ pwmo [7:0] $end
$var wire 1 % rd $end
$var wire 1 & rst $end
$var wire 1 ' wr $end
$var reg 32 ( dinf [31:0] $end
$var reg 32 ) dout [31:0] $end
$var reg 32 * duty0 [31:0] $end
$var reg 32 + duty1 [31:0] $end
$var reg 32 , duty2 [31:0] $end
$var reg 32 - duty3 [31:0] $end
$var reg 32 . duty4 [31:0] $end
$var reg 32 / duty5 [31:0] $end
$var reg 32 0 duty6 [31:0] $end
$var reg 32 1 duty7 [31:0] $end
$var reg 1 2 en0 $end
$var reg 1 3 en1 $end
$var reg 1 4 en2 $end
$var reg 1 5 en3 $end
$var reg 1 6 en4 $end
$var reg 1 7 en5 $end
$var reg 1 8 en6 $end
$var reg 1 9 en7 $end
$var reg 32 : period0 [31:0] $end
$var reg 32 ; period1 [31:0] $end
$var reg 32 < period2 [31:0] $end
$var reg 32 = period3 [31:0] $end
$var reg 32 > period4 [31:0] $end
$var reg 32 ? period5 [31:0] $end
$var reg 32 @ period6 [31:0] $end
$var reg 32 A period7 [31:0] $end
$scope module pwm0 $end
$var wire 1 " clk $end
$var wire 32 B duty [31:0] $end
$var wire 1 C en $end
$var wire 32 D period [31:0] $end
$var reg 15 E contmsec [14:0] $end
$var reg 6 F contusec [5:0] $end
$var reg 5 G dutyf [4:0] $end
$var reg 5 H periodf [4:0] $end
$var reg 1 I state $end
$upscope $end
$scope module pwm1 $end
$var wire 1 " clk $end
$var wire 32 J duty [31:0] $end
$var wire 1 K en $end
$var wire 32 L period [31:0] $end
$var reg 15 M contmsec [14:0] $end
$var reg 6 N contusec [5:0] $end
$var reg 5 O dutyf [4:0] $end
$var reg 5 P periodf [4:0] $end
$var reg 1 Q state $end
$upscope $end
$scope module pwm2 $end
$var wire 1 " clk $end
$var wire 32 R duty [31:0] $end
$var wire 1 S en $end
$var wire 32 T period [31:0] $end
$var reg 15 U contmsec [14:0] $end
$var reg 6 V contusec [5:0] $end
$var reg 5 W dutyf [4:0] $end
$var reg 5 X periodf [4:0] $end
$var reg 1 Y state $end
$upscope $end
$scope module pwm3 $end
$var wire 1 " clk $end
$var wire 32 Z duty [31:0] $end
$var wire 1 [ en $end
$var wire 32 \ period [31:0] $end
$var reg 15 ] contmsec [14:0] $end
$var reg 6 ^ contusec [5:0] $end
$var reg 5 _ dutyf [4:0] $end
$var reg 5 ` periodf [4:0] $end
$var reg 1 a state $end
$upscope $end
$scope module pwm4 $end
$var wire 1 " clk $end
$var wire 32 b duty [31:0] $end
$var wire 1 c en $end
$var wire 32 d period [31:0] $end
$var reg 15 e contmsec [14:0] $end
$var reg 6 f contusec [5:0] $end
$var reg 5 g dutyf [4:0] $end
$var reg 5 h periodf [4:0] $end
$var reg 1 i state $end
$upscope $end
$scope module pwm5 $end
$var wire 1 " clk $end
$var wire 32 j duty [31:0] $end
$var wire 1 k en $end
$var wire 32 l period [31:0] $end
$var reg 15 m contmsec [14:0] $end
$var reg 6 n contusec [5:0] $end
$var reg 5 o dutyf [4:0] $end
$var reg 5 p periodf [4:0] $end
$var reg 1 q state $end
$upscope $end
$scope module pwm6 $end
$var wire 1 " clk $end
$var wire 32 r duty [31:0] $end
$var wire 1 s en $end
$var wire 32 t period [31:0] $end
$var reg 15 u contmsec [14:0] $end
$var reg 6 v contusec [5:0] $end
$var reg 5 w dutyf [4:0] $end
$var reg 5 x periodf [4:0] $end
$var reg 1 y state $end
$upscope $end
$scope module pwm7 $end
$var wire 1 " clk $end
$var wire 32 z duty [31:0] $end
$var wire 1 { en $end
$var wire 32 | period [31:0] $end
$var reg 15 } contmsec [14:0] $end
$var reg 6 ~ contusec [5:0] $end
$var reg 5 !" dutyf [4:0] $end
$var reg 5 "" periodf [4:0] $end
$var reg 1 #" state $end
$upscope $end
$upscope $end
$upscope $end
$enddefinitions $end
#0
$dumpvars
x#"
b0 ""
b0 !"
b0 ~
b0 }
bx |
x{
bx z
xy
b0 x
b0 w
b0 v
b0 u
bx t
xs
bx r
xq
b0 p
b0 o
b0 n
b0 m
bx l
xk
bx j
xi
b0 h
b0 g
b0 f
b0 e
bx d
xc
bx b
xa
b0 `
b0 _
b0 ^
b0 ]
bx \
x[
bx Z
xY
b0 X
b0 W
b0 V
b0 U
bx T
xS
bx R
xQ
b0 P
b0 O
b0 N
b0 M
bx L
xK
bx J
xI
b0 H
b0 G
b0 F
b0 E
bx D
xC
b10 B
bx A
bx @
bx ?
bx >
bx =
bx <
bx ;
bx :
x9
x8
x7
x6
x5
x4
x3
x2
bx 1
bx 0
bx /
bx .
bx -
bx ,
bx +
b10 *
bx )
b10 (
1'
x&
x%
bx $
b10 #
1"
b1000 !
$end
#1
0"
#2
b10100 :
b10100 D
b10100 (
1"
b100 !
b10100 #
#3
0"
#4
b1 F
1I
bx1 $
12
1C
b1 (
1"
b0 !
b1 #
#5
0"
#6
b100 +
b100 J
b100 (
b10 F
1"
b10100 !
b100 #
#7
0"
#8
b11 F
b10100 ;
b10100 L
b10100 (
1"
b10000 !
b10100 #
#9
0"
#10
13
1K
b1 (
b100 F
1"
b1100 !
b1 #
#11
0"
#12
b101 F
b1 N
1Q
bx11 $
b10 ,
b10 R
b10 (
1"
b100000 !
b10 #
#13
0"
#14
b10100 <
b10100 T
b10100 (
b10 N
b110 F
1"
b11100 !
b10100 #
#15
0"
#16
b111 F
b11 N
b1 V
1Y
bx111 $
14
1S
b1 (
1"
b11000 !
b1 #
#17
0"
#18
b10 /
b10 j
b10 (
b10 V
b100 N
b1000 F
1"
b1000100 !
b10 #
#19
0"
#20
b1001 F
b101 N
b11 V
b10100 ?
b10100 l
b10100 (
1"
b1000000 !
b10100 #
#21
0"
#22
17
1k
b1 (
b100 V
b110 N
b1010 F
1"
b111100 !
b1 #
#23
0"
#24
b1011 F
b111 N
b101 V
b1 n
1q
bx1xx111 $
b10 1
b10 z
b10 (
1"
b1011100 !
b10 #
#25
0"
#26
b10100 A
b10100 |
b10100 (
b10 n
b110 V
b1000 N
b1100 F
1"
b1011000 !
b10100 #
#27
0"
#28
b1101 F
b1001 N
b111 V
b11 n
b1 ~
1#"
b1x1xx111 $
19
1{
b1 (
1"
b1010100 !
b1 #
#29
0"
#30
b10100 )
b10 ~
b100 n
b1000 V
b1010 N
b1110 F
1"
b100 !
1%
0'
#31
0"
#32
b1111 F
b1011 N
b1001 V
b101 n
b11 ~
b1 )
1"
b11000 !
#33
0"
#34
b100 ~
b110 n
b1010 V
b1100 N
b10000 F
1"
b1011100 !
#35
0"
#36
b10001 F
b1101 N
b1011 V
b111 n
b101 ~
1"
b0 !
#37
0"
#38
b10100 )
b110 ~
b1000 n
b1100 V
b1110 N
b10010 F
1"
b100 !
#39
0"
#40
b10011 F
b1111 N
b1101 V
b1001 n
b111 ~
1"
#41
0"
#42
b1000 ~
b1010 n
b1110 V
b10000 N
b10100 F
1"
#43
0"
#44
b10101 F
b10001 N
b1111 V
b1011 n
b1001 ~
1"
#45
0"
#46
b1010 ~
b1100 n
b10000 V
b10010 N
b10110 F
1"
#47
0"
#48
b10111 F
b10011 N
b10001 V
b1101 n
b1011 ~
1"
#49
0"
#50
b1100 ~
b1110 n
b10010 V
b10100 N
b11000 F
1"
#51
0"
#52
b11001 F
b10101 N
b10011 V
b1111 n
b1101 ~
1"
#53
0"
#54
b1110 ~
b10000 n
b10100 V
b10110 N
b11010 F
1"
#55
0"
#56
b11011 F
b10111 N
b10101 V
b10001 n
b1111 ~
1"
#57
0"
#58
b10000 ~
b10010 n
b10110 V
b11000 N
b11100 F
1"
#59
0"
#60
b11101 F
b11001 N
b10111 V
b10011 n
b10001 ~
1"
#61
0"
#62
b10010 ~
b10100 n
b11000 V
b11010 N
b11110 F
1"
#63
0"
#64
b11111 F
b11011 N
b11001 V
b10101 n
b10011 ~
1"
#65
0"
#66
b10100 ~
b10110 n
b11010 V
b11100 N
b100000 F
1"
#67
0"
#68
b100001 F
b11101 N
b11011 V
b10111 n
b10101 ~
1"
#69
0"
#70
b10110 ~
b11000 n
b11100 V
b11110 N
b100010 F
1"
#71
0"
#72
b100011 F
b11111 N
b11101 V
b11001 n
b10111 ~
1"
#73
0"
#74
b11000 ~
b11010 n
b11110 V
b100000 N
b100100 F
1"
#75
0"
#76
b100101 F
b100001 N
b11111 V
b11011 n
b11001 ~
1"
#77
0"
#78
b11010 ~
b11100 n
b100000 V
b100010 N
b100110 F
1"
#79
0"
#80
b100111 F
b100011 N
b100001 V
b11101 n
b11011 ~
1"
#81
0"
#82
b11100 ~
b11110 n
b100010 V
b100100 N
b101000 F
1"
#83
0"
#84
b101001 F
b100101 N
b100011 V
b11111 n
b11101 ~
1"
#85
0"
#86
b11110 ~
b100000 n
b100100 V
b100110 N
b101010 F
1"
#87
0"
#88
b101011 F
b100111 N
b100101 V
b100001 n
b11111 ~
1"
#89
0"
#90
b100000 ~
b100010 n
b100110 V
b101000 N
b101100 F
1"
#91
0"
#92
b101101 F
b101001 N
b100111 V
b100011 n
b100001 ~
1"
#93
0"
#94
b100010 ~
b100100 n
b101000 V
b101010 N
b101110 F
1"
#95
0"
#96
b101111 F
b101011 N
b101001 V
b100101 n
b100011 ~
1"
#97
0"
#98
b100100 ~
b100110 n
b101010 V
b101100 N
b110000 F
1"
#99
0"
#100
b110001 F
b101101 N
b101011 V
b100111 n
b100101 ~
1"
#101
0"
#102
b100110 ~
b101000 n
b101100 V
b101110 N
b110010 F
1"
#103
0"
#104
b1 E
b0 F
b101111 N
b101101 V
b101001 n
b100111 ~
1"
#105
0"
#106
b101000 ~
b101010 n
b101110 V
b110000 N
b1 F
1"
#107
0"
#108
b10 F
b110001 N
b101111 V
b101011 n
b101001 ~
1"
#109
0"
#110
b101010 ~
b101100 n
b110000 V
b110010 N
b11 F
1"
#111
0"
#112
b100 F
b1 M
b0 N
b110001 V
b101101 n
b101011 ~
1"
#113
0"
#114
b101100 ~
b101110 n
b110010 V
b1 N
b101 F
1"
#115
0"
#116
b110 F
b10 N
b1 U
b0 V
b101111 n
b101101 ~
1"
#117
0"
#118
b101110 ~
b110000 n
b1 V
b11 N
b111 F
1"
#119
0"
#120
b1000 F
b100 N
b10 V
b110001 n
b101111 ~
1"
#121
0"
#122
b110000 ~
b110010 n
b11 V
b101 N
b1001 F
1"
#123
0"
#124
b1010 F
b110 N
b100 V
b1 m
b0 n
b110001 ~
1"
#125
0"
#126
b110010 ~
b1 n
b101 V
b111 N
b1011 F
1"
#127
0"
#128
b1100 F
b1000 N
b110 V
b10 n
b1 }
b0 ~
1"
#129
0"
#130
b1 ~
b11 n
b111 V
b1001 N
b1101 F
1"
#131
0"
#132
b1110 F
b1010 N
b1000 V
b100 n
b10 ~
1"
#133
0"
#134
b11 ~
b101 n
b1001 V
b1011 N
b1111 F
1"
#135
0"
#136
b10000 F
b1100 N
b1010 V
b110 n
b100 ~
1"
#137
0"
#138
b101 ~
b111 n
b1011 V
b1101 N
b10001 F
1"
#139
0"
#140
b10010 F
b1110 N
b1100 V
b1000 n
b110 ~
1"
#141
0"
#142
b111 ~
b1001 n
b1101 V
b1111 N
b10011 F
1"
#143
0"
#144
b10100 F
b10000 N
b1110 V
b1010 n
b1000 ~
1"
#145
0"
#146
b1001 ~
b1011 n
b1111 V
b10001 N
b10101 F
1"
#147
0"
#148
b10110 F
b10010 N
b10000 V
b1100 n
b1010 ~
1"
#149
0"
#150
b1011 ~
b1101 n
b10001 V
b10011 N
b10111 F
1"
#151
0"
#152
b11000 F
b10100 N
b10010 V
b1110 n
b1100 ~
1"
#153
0"
#154
b1101 ~
b1111 n
b10011 V
b10101 N
b11001 F
1"
#155
0"
#156
b11010 F
b10110 N
b10100 V
b10000 n
b1110 ~
1"
#157
0"
#158
b1111 ~
b10001 n
b10101 V
b10111 N
b11011 F
1"
#159
0"
#160
b11100 F
b11000 N
b10110 V
b10010 n
b10000 ~
1"
#161
0"
#162
b10001 ~
b10011 n
b10111 V
b11001 N
b11101 F
1"
#163
0"
#164
b11110 F
b11010 N
b11000 V
b10100 n
b10010 ~
1"
#165
0"
#166
b10011 ~
b10101 n
b11001 V
b11011 N
b11111 F
1"
#167
0"
#168
b100000 F
b11100 N
b11010 V
b10110 n
b10100 ~
1"
#169
0"
#170
b10101 ~
b10111 n
b11011 V
b11101 N
b100001 F
1"
#171
0"
#172
b100010 F
b11110 N
b11100 V
b11000 n
b10110 ~
1"
#173
0"
#174
b10111 ~
b11001 n
b11101 V
b11111 N
b100011 F
1"
#175
0"
#176
b100100 F
b100000 N
b11110 V
b11010 n
b11000 ~
1"
#177
0"
#178
b11001 ~
b11011 n
b11111 V
b100001 N
b100101 F
1"
#179
0"
#180
b100110 F
b100010 N
b100000 V
b11100 n
b11010 ~
1"
#181
0"
#182
b11011 ~
b11101 n
b100001 V
b100011 N
b100111 F
1"
#183
0"
#184
b101000 F
b100100 N
b100010 V
b11110 n
b11100 ~
1"
#185
0"
#186
b11101 ~
b11111 n
b100011 V
b100101 N
b101001 F
1"
#187
0"
#188
b101010 F
b100110 N
b100100 V
b100000 n
b11110 ~
1"
#189
0"
#190
b11111 ~
b100001 n
b100101 V
b100111 N
b101011 F
1"
#191
0"
#192
b101100 F
b101000 N
b100110 V
b100010 n
b100000 ~
1"
#193
0"
#194
b100001 ~
b100011 n
b100111 V
b101001 N
b101101 F
1"
#195
0"
#196
b101110 F
b101010 N
b101000 V
b100100 n
b100010 ~
1"
#197
0"
#198
b100011 ~
b100101 n
b101001 V
b101011 N
b101111 F
1"
#199
0"
#200
b110000 F
b101100 N
b101010 V
b100110 n
b100100 ~
1"
#201
0"
#202
b100101 ~
b100111 n
b101011 V
b101101 N
b110001 F
1"
#203
0"
#204
b110010 F
b101110 N
b101100 V
b101000 n
b100110 ~
1"
#205
0"
#206
b100111 ~
b101001 n
b101101 V
b101111 N
0I
b1x1xx110 $
b10 E
b0 F
1"
#207
0"
#208
b1 F
b110000 N
b101110 V
b101010 n
b101000 ~
1"
#209
0"
#210
b101001 ~
b101011 n
b101111 V
b110001 N
b10 F
1"
#211
0"
#212
b11 F
b110010 N
b110000 V
b101100 n
b101010 ~
1"
#213
0"
#214
b101011 ~
b101101 n
b110001 V
b10 M
b0 N
b100 F
1"
#215
0"
#216
b101 F
b1 N
b110010 V
b101110 n
b101100 ~
1"
#217
0"
#218
b101101 ~
b101111 n
0Y
b1x1xx010 $
b10 U
b0 V
b10 N
b110 F
1"
#219
0"
#220
b111 F
b11 N
b1 V
b110000 n
b101110 ~
1"
#221
0"
#222
b101111 ~
b110001 n
b10 V
b100 N
b1000 F
1"
#223
0"
#224
b1001 F
b101 N
b11 V
b110010 n
b110000 ~
1"
#225
0"
#226
b110001 ~
0q
b1x0xx010 $
b10 m
b0 n
b100 V
b110 N
b1010 F
1"
#227
0"
#228
b1011 F
b111 N
b101 V
b1 n
b110010 ~
1"
#229
0"
#230
0#"
b0x0xx010 $
b10 }
b0 ~
b10 n
b110 V
b1000 N
b1100 F
1"
#231
0"
#232
b1101 F
b1001 N
b111 V
b11 n
b1 ~
1"
#233
0"
#234
b10 ~
b100 n
b1000 V
b1010 N
b1110 F
1"
#235
0"
#236
b1111 F
b1011 N
b1001 V
b101 n
b11 ~
1"
#237
0"
#238
b100 ~
b110 n
b1010 V
b1100 N
b10000 F
1"
#239
0"
#240
b10001 F
b1101 N
b1011 V
b111 n
b101 ~
1"
#241
0"
#242
b110 ~
b1000 n
b1100 V
b1110 N
b10010 F
1"
#243
0"
#244
b10011 F
b1111 N
b1101 V
b1001 n
b111 ~
1"
#245
0"
#246
b1000 ~
b1010 n
b1110 V
b10000 N
b10100 F
1"
#247
0"
#248
b10101 F
b10001 N
b1111 V
b1011 n
b1001 ~
1"
#249
0"
#250
b1010 ~
b1100 n
b10000 V
b10010 N
b10110 F
1"
#251
0"
#252
b10111 F
b10011 N
b10001 V
b1101 n
b1011 ~
1"
#253
0"
#254
b1100 ~
b1110 n
b10010 V
b10100 N
b11000 F
1"
#255
0"
#256
b11001 F
b10101 N
b10011 V
b1111 n
b1101 ~
1"
#257
0"
#258
b1110 ~
b10000 n
b10100 V
b10110 N
b11010 F
1"
#259
0"
#260
b11011 F
b10111 N
b10101 V
b10001 n
b1111 ~
1"
#261
0"
#262
b10000 ~
b10010 n
b10110 V
b11000 N
b11100 F
1"
#263
0"
#264
b11101 F
b11001 N
b10111 V
b10011 n
b10001 ~
1"
#265
0"
#266
b10010 ~
b10100 n
b11000 V
b11010 N
b11110 F
1"
#267
0"
#268
b11111 F
b11011 N
b11001 V
b10101 n
b10011 ~
1"
#269
0"
#270
b10100 ~
b10110 n
b11010 V
b11100 N
b100000 F
1"
#271
0"
#272
b100001 F
b11101 N
b11011 V
b10111 n
b10101 ~
1"
#273
0"
#274
b10110 ~
b11000 n
b11100 V
b11110 N
b100010 F
1"
#275
0"
#276
b100011 F
b11111 N
b11101 V
b11001 n
b10111 ~
1"
#277
0"
#278
b11000 ~
b11010 n
b11110 V
b100000 N
b100100 F
1"
#279
0"
#280
b100101 F
b100001 N
b11111 V
b11011 n
b11001 ~
1"
#281
0"
#282
b11010 ~
b11100 n
b100000 V
b100010 N
b100110 F
1"
#283
0"
#284
b100111 F
b100011 N
b100001 V
b11101 n
b11011 ~
1"
#285
0"
#286
b11100 ~
b11110 n
b100010 V
b100100 N
b101000 F
1"
#287
0"
#288
b101001 F
b100101 N
b100011 V
b11111 n
b11101 ~
1"
#289
0"
#290
b11110 ~
b100000 n
b100100 V
b100110 N
b101010 F
1"
#291
0"
#292
b101011 F
b100111 N
b100101 V
b100001 n
b11111 ~
1"
#293
0"
#294
b100000 ~
b100010 n
b100110 V
b101000 N
b101100 F
1"
#295
0"
#296
b101101 F
b101001 N
b100111 V
b100011 n
b100001 ~
1"
#297
0"
#298
b100010 ~
b100100 n
b101000 V
b101010 N
b101110 F
1"
#299
0"
#300
b101111 F
b101011 N
b101001 V
b100101 n
b100011 ~
1"
#301
0"
#302
b100100 ~
b100110 n
b101010 V
b101100 N
b110000 F
1"
#303
0"
#304
b110001 F
b101101 N
b101011 V
b100111 n
b100101 ~
1"
#305
0"
#306
b100110 ~
b101000 n
b101100 V
b101110 N
b110010 F
1"
#307
0"
#308
b11 E
b0 F
b101111 N
b101101 V
b101001 n
b100111 ~
1"
#309
0"
#310
b101000 ~
b101010 n
b101110 V
b110000 N
b1 F
1"
#311
0"
#312
b10 F
b110001 N
b101111 V
b101011 n
b101001 ~
1"
#313
0"
#314
b101010 ~
b101100 n
b110000 V
b110010 N
b11 F
1"
#315
0"
#316
b100 F
b11 M
b0 N
b110001 V
b101101 n
b101011 ~
1"
#317
0"
#318
b101100 ~
b101110 n
b110010 V
b1 N
b101 F
1"
#319
0"
#320
b110 F
b10 N
b11 U
b0 V
b101111 n
b101101 ~
1"
#321
0"
#322
b101110 ~
b110000 n
b1 V
b11 N
b111 F
1"
#323
0"
#324
b1000 F
b100 N
b10 V
b110001 n
b101111 ~
1"
#325
0"
#326
b110000 ~
b110010 n
b11 V
b101 N
b1001 F
1"
#327
0"
#328
b1010 F
b110 N
b100 V
b11 m
b0 n
b110001 ~
1"
#329
0"
#330
b110010 ~
b1 n
b101 V
b111 N
b1011 F
1"
#331
0"
#332
b1100 F
b1000 N
b110 V
b10 n
b11 }
b0 ~
1"
#333
0"
#334
b1 ~
b11 n
b111 V
b1001 N
b1101 F
1"
#335
0"
#336
b1110 F
b1010 N
b1000 V
b100 n
b10 ~
1"
#337
0"
#338
b11 ~
b101 n
b1001 V
b1011 N
b1111 F
1"
#339
0"
#340
b10000 F
b1100 N
b1010 V
b110 n
b100 ~
1"
#341
0"
#342
b101 ~
b111 n
b1011 V
b1101 N
b10001 F
1"
#343
0"
#344
b10010 F
b1110 N
b1100 V
b1000 n
b110 ~
1"
#345
0"
#346
b111 ~
b1001 n
b1101 V
b1111 N
b10011 F
1"
#347
0"
#348
b10100 F
b10000 N
b1110 V
b1010 n
b1000 ~
1"
#349
0"
#350
b1001 ~
b1011 n
b1111 V
b10001 N
b10101 F
1"
#351
0"
#352
b10110 F
b10010 N
b10000 V
b1100 n
b1010 ~
1"
#353
0"
#354
b1011 ~
b1101 n
b10001 V
b10011 N
b10111 F
1"
#355
0"
#356
b11000 F
b10100 N
b10010 V
b1110 n
b1100 ~
1"
#357
0"
#358
b1101 ~
b1111 n
b10011 V
b10101 N
b11001 F
1"
#359
0"
#360
b11010 F
b10110 N
b10100 V
b10000 n
b1110 ~
1"
#361
0"
#362
b1111 ~
b10001 n
b10101 V
b10111 N
b11011 F
1"
#363
0"
#364
b11100 F
b11000 N
b10110 V
b10010 n
b10000 ~
1"
#365
0"
#366
b10001 ~
b10011 n
b10111 V
b11001 N
b11101 F
1"
#367
0"
#368
b11110 F
b11010 N
b11000 V
b10100 n
b10010 ~
1"
#369
0"
#370
b10011 ~
b10101 n
b11001 V
b11011 N
b11111 F
1"
#371
0"
#372
b100000 F
b11100 N
b11010 V
b10110 n
b10100 ~
1"
#373
0"
#374
b10101 ~
b10111 n
b11011 V
b11101 N
b100001 F
1"
#375
0"
#376
b100010 F
b11110 N
b11100 V
b11000 n
b10110 ~
1"
#377
0"
#378
b10111 ~
b11001 n
b11101 V
b11111 N
b100011 F
1"
#379
0"
#380
b100100 F
b100000 N
b11110 V
b11010 n
b11000 ~
1"
#381
0"
#382
b11001 ~
b11011 n
b11111 V
b100001 N
b100101 F
1"
#383
0"
#384
b100110 F
b100010 N
b100000 V
b11100 n
b11010 ~
1"
#385
0"
#386
b11011 ~
b11101 n
b100001 V
b100011 N
b100111 F
1"
#387
0"
#388
b101000 F
b100100 N
b100010 V
b11110 n
b11100 ~
1"
#389
0"
#390
b11101 ~
b11111 n
b100011 V
b100101 N
b101001 F
1"
#391
0"
#392
b101010 F
b100110 N
b100100 V
b100000 n
b11110 ~
1"
#393
0"
#394
b11111 ~
b100001 n
b100101 V
b100111 N
b101011 F
1"
#395
0"
#396
b101100 F
b101000 N
b100110 V
b100010 n
b100000 ~
1"
#397
0"
#398
b100001 ~
b100011 n
b100111 V
b101001 N
b101101 F
1"
#399
0"
#400
b101110 F
b101010 N
b101000 V
b100100 n
b100010 ~
1"
#401
0"
#402
b100011 ~
b100101 n
b101001 V
b101011 N
b101111 F
1"
#403
0"
#404
b110000 F
b101100 N
b101010 V
b100110 n
b100100 ~
1"
#405
0"
#406
b100101 ~
b100111 n
b101011 V
b101101 N
b110001 F
1"
#407
0"
#408
b110010 F
b101110 N
b101100 V
b101000 n
b100110 ~
1"
#409
0"
#410
b100111 ~
b101001 n
b101101 V
b101111 N
b100 E
b0 F
1"
#411
0"
#412
b1 F
b110000 N
b101110 V
b101010 n
b101000 ~
1"
#413
0"
#414
b101001 ~
b101011 n
b101111 V
b110001 N
b10 F
1"
#415
0"
#416
b11 F
b110010 N
b110000 V
b101100 n
b101010 ~
1"
#417
0"
#418
b101011 ~
b101101 n
b110001 V
0Q
b0x0xx000 $
b100 M
b0 N
b100 F
1"
#419
0"
#420
b101 F
b1 N
b110010 V
b101110 n
b101100 ~
1"
#421
0"
#422
b101101 ~
b101111 n
b100 U
b0 V
b10 N
b110 F
1"
#423
0"
#424
b111 F
b11 N
b1 V
b110000 n
b101110 ~
1"
#425
0"
#426
b101111 ~
b110001 n
b10 V
b100 N
b1000 F
1"
#427
0"
